pydeezer/__init__.py
pydeezer-1.1.0.dist-info/DESCRIPTION.rst
pydeezer-1.1.0.dist-info/METADATA
pydeezer-1.1.0.dist-info/RECORD
pydeezer-1.1.0.dist-info/WHEEL
pydeezer-1.1.0.dist-info/metadata.json
pydeezer-1.1.0.dist-info/pbr.json
pydeezer-1.1.0.dist-info/top_level.txt
