Metadata-Version: 2.0
Name: pydeezer
Version: 1.1.0
Summary: A simple Python wrapper for Deezer's API
Home-page: https://github.com/rcrdclub/pydeezer
Author: Hery Ratsimihah
Author-email: UNKNOWN
License: MIT
Keywords: deezer api library
Platform: UNKNOWN
Classifier: Development Status :: 4 - Beta
Classifier: Intended Audience :: Developers
Classifier: Natural Language :: English
Classifier: License :: OSI Approved :: MIT License
Classifier: Programming Language :: Python :: 2.7
Requires-Dist: requests
